graphviz_overlay/__init__.py
graphviz_overlay/graph.py
graphviz_overlay/overlays/__init__.py
graphviz_overlay/overlays/er.py
graphviz_overlay/overlays/graphviz.py
graphviz_overlay-0.1.1.dist-info/entry_points.txt
graphviz_overlay-0.1.1.dist-info/WHEEL
graphviz_overlay-0.1.1.dist-info/METADATA
graphviz_overlay-0.1.1.dist-info/RECORD
